nunpyyy/__init__.py
nunpyyy/main.py
nunpyyy-0.1.0.dist-info/METADATA
nunpyyy-0.1.0.dist-info/WHEEL
nunpyyy-0.1.0.dist-info/top_level.txt
nunpyyy-0.1.0.dist-info/RECORD
